netlink/datadog/sap/__init__.py
netlink/datadog/sap/abap/__init__.py
netlink/datadog/sap/abap/rfc_transactional_calls.py
netlink/datadog/sap/abap_worker.py
netlink/datadog/sap/cli.py
netlink/datadog/sap/datadog_sap.py
netlink/datadog/sap/load_configuration.py
netlink_datadog_sap-0.0.1.dist-info/entry_points.txt
netlink_datadog_sap-0.0.1.dist-info/WHEEL
netlink_datadog_sap-0.0.1.dist-info/METADATA
netlink_datadog_sap-0.0.1.dist-info/RECORD
